aopera/__init__.py
aopera/aopsd.py
aopera/control.py
aopera/ffwfs.py
aopera/fiber.py
aopera/otfpsf.py
aopera/photometry.py
aopera/readconfig.py
aopera/shwfs.py
aopera/simulation.py
aopera/trajectory.py
aopera/turbulence.py
aopera/utils.py
aopera/variance.py
aopera/zernike.py
aopera/data/ekarus.ini
aopera/data/harmoni-scao.ini
aopera/data/ohp.ini
aopera/data/papyrus.ini
aopera/data/paranal.ini
aopera/data/sphere.ini
aopera-0.1.0.dist-info/licenses/LICENSE
aopera-0.1.0.dist-info/METADATA
aopera-0.1.0.dist-info/WHEEL
aopera-0.1.0.dist-info/top_level.txt
aopera-0.1.0.dist-info/RECORD
