Metadata-Version: 2.4
Name: aopera
Version: 0.1.0
Summary: Simulation of AO residuals through phase PSD budget
Home-page: https://gitlab.lam.fr/lam-grd-public/aopera.git
Author: Romain JL Fetick (ONERA Chatillon, France)
Author-email: Romain Fetick <romain.fetick@lam.fr>
License:                     GNU GENERAL PUBLIC LICENSE
Project-URL: repository, https://gitlab.lam.fr/lam-grd-public/aopera.git
Keywords: PSF,AO,adaptive optics
Requires: numpy
Requires: scipy
Requires-Python: >=3.0
License-File: LICENSE
Requires-Dist: numpy
Requires-Dist: scipy
Dynamic: author
Dynamic: home-page
Dynamic: license-file
Dynamic: requires
